LICENSE
MANIFEST.in
README.md
requirements.txt
setup.py
kindred/CandidateBuilder.py
kindred/CandidateRelation.py
kindred/Corpus.py
kindred/Document.py
kindred/Entity.py
kindred/EntityRecognizer.py
kindred/LogisticRegressionWithThreshold.py
kindred/MultiLabelClassifier.py
kindred/Parser.py
kindred/Relation.py
kindred/RelationClassifier.py
kindred/Sentence.py
kindred/Token.py
kindred/Vectorizer.py
kindred/__init__.py
kindred/bionlpst.py
kindred/bionlpst_files.txt
kindred/datageneration.py
kindred/defunctFileWarning.py
kindred/evalFunctions.py
kindred/loadFunctions.py
kindred/manualAnnotation.py
kindred/pubannotation.py
kindred/pubtator.py
kindred/saveFunctions.py
kindred/utils.py
kindred.egg-info/PKG-INFO
kindred.egg-info/SOURCES.txt
kindred.egg-info/dependency_links.txt
kindred.egg-info/not-zip-safe
kindred.egg-info/requires.txt
kindred.egg-info/top_level.txt